{
    "clauseField": "23",
    "ftcCnclsns": "2",
    "clauseArticle": [
        "제5조(운임 및 요금의 지불)\n3. 대한민국 내에서 운임 및 요금을 원화로 지불하는 경우의 적용환율은 다음 각 호의 정하는 바에 의한다.\n나. 위 가호에도 불구하고 전일까지 적용되어온 당해 주의 환율과 비교, 환율의 변동폭이 1퍼센트 이상 발생하였을 경우에는 변동된 신 환율을 익일부터 당해 3주일간의 잔여기간 동안 사용한다."
    ],
    "dvAntageous": "1",
    "comProvision": [
        "제5조(운임 및 요금의 지불)\n3. 대한민국 내에서 운임 및 요금을 원화로 지불하는 경우의 적용환율은 다음 각 호의 정하는 바에 의한다.\n나. 위 가호에도 불구하고 전일까지 적용되어온 당해 주의 환율과 비교, 환율의 변동폭이 1퍼센트 이상 발생하였을 경우에는 변동된 신 환율을 익일부터 당해 1주일간의 잔여기간 동안 사용한다."
    ]
}