{
    "clauseField": "2",
    "ftcCnclsns": "1",
    "clauseArticle": [
        "(000 공급계약서)\n제5조 위약금\nPOS시스템 : 정상 판매금액\n포스프로그램사용료 : 관리비*(36개월-사용개월수)\n자동이체관리비(DDC) : 관리비*36개월\n000사용료 : 000사용료*36개월 "
    ],
    "dvAntageous": "2",
    "illdcssBasiss": [
        "통상 제품의 임대차 계약에서 계약해지시 위약금은 제품의 사용기간이나 감가상각의 정도 등을 감안하여 정해지는 것이 일반적이다.",
        "가맹점은 당해 계약기간이 만료될 때까지 관리비와 사용료 명목으로 매월 일정금액을 납부하고 있는 점을 감안할 때 가맹점이 계약해지 이후에는 서비스를 제공받지 않음에도 계약기간 전체에 대하여 서비스를 제공받는 경우보다 실질적으로 더 많은 비용을 부담하게 하고 있는 것으로 보인다.",
        "해당 약관조항은 고객에게 부당하게 과중한 손해배상의무를 부담시키는 조항이다."
    ],
    "relateLaword": [
        "제8조(손해배상액의 예정) \n고객에게 부당하게 과중한 지연 손해금 등의 손해배상 의무를 부담시키는 약관 조항은 무효로 한다."
    ],
    "unfavorableProvision": "2"
}