{
    "clauseField": "1",
    "ftcCnclsns": "1",
    "clauseArticle": [
        "제24조(조항의 해석)\n제1항 본 계약 조항 중  갑 과  을 간에 해석상의 차이가 있을 시  갑 의 해석이 우선한다."
    ],
    "dvAntageous": "2",
    "illdcssBasiss": [
        "약관의규제에관한법률 제5조제1항에 따르면 약관은 신의성실의 원칙에 따라 공정하게 해석되어야 하며…… , 또한 동법 제5조제2항에 따르면 약관의 뜻이 명백하지 아니한 경우에는 고객에게 유리하게 해석되어야 한다. 라고 규정되어 있는 바, 위 약관조항은 신의성실의 원칙에 반하여 공정을 잃은 약관조항이다."
    ],
    "relateLaword": [
        "제6조(일반원칙) \n① 신의성실의 원칙을 위반하여 공정성을 잃은 약관 조항은 무효이다."
    ],
    "unfavorableProvision": "1"
}