{
    "clauseField": "39",
    "ftcCnclsns": "1",
    "clauseArticle": [
        "제27조(사용료의 반환) \n제3조 을은 회원탈퇴시 아래의 사항을 준수한다.\n제3항 환불금은 부가세 10퍼센트, 등록비용 10퍼센트, 사용기간 월 정산금액(1일 이용도월 기준) 공제 후 환불        ㅇ 카드 사용시 카드수수료 5퍼센트공제        \nㅇ 지급된 용품금액의 공제"
    ],
    "dvAntageous": "2",
    "illdcssBasiss": [
        "일반 거래관행상 거래금액의 10퍼센트를 위약금으로 함이 통상적임을 고려할 때 부가세 및 등록금의 명목으로 이용대금의 각 10퍼센트, 총 20퍼센트를 공제하는 것은 과다하다 할 것이다. ",
        "이용대금의 공제 관련, 총 이용대금 중 이용기간에 해당하는 금액을 공제하여야 할 것임에도 불구하고 무조건 한달 이용대금을 공제하도록 하고 있어 단기간 이용 후 계약을 해지하는 고객에게 지나치게 불리하다. ",
        "소비자분쟁해결기준 및 체육단련장 표준약관에서는 계약의 중도해지시 총 이용금액에서 이용일수에 해당하는 이용금액 및 총이용금액의 10퍼센트를 공제한 후 이용대금을 환급하도록 하고 있다. ",
        "해당 약관조항은 고객에게 부당하게 과중한 손해배상의무를 부담시키는 조항 또는 계약의 해지로 인한 사업자의 원상회복의무를 부당하게 경감하는 조항이다."
    ],
    "relateLaword": [
        "제8조(손해배상액의 예정) \n고객에게 부당하게 과중한 지연 손해금 등의 손해배상 의무를 부담시키는 약관 조항은 무효로 한다.",
        "제9조(계약의 해제, 해지) \n계약의 해제, 해지에 관하여 정하고 있는 약관의 내용 중 다음 각 호의 어느 하나에 해당되는 내용을 정하고 있는 조항은 무효로 한다.\n  4. 계약의 해제 또는 해지로 인한 원상회복의무를 상당한 이유 없이 고객에게 과중하게 부담시키거나 고객의 원상회복 청구권을 부당하게 포기하도록 하는 조항"
    ],
    "unfavorableProvision": "2"
}