{
    "clauseField": "3",
    "ftcCnclsns": "1",
    "clauseArticle": [
        "제6조(계약의 해제등)\n제1항. 갑은 을이 다음 각호에 해당할 경우 본 계약을 해제할 수 있다.\n제1항 3호. 다른 분양자나 상인을 선동하여 전체사업에 지장을 초래할 때"
    ],
    "dvAntageous": "2",
    "illdcssBasiss": [
        "상인을 선동하여 사업진행에 지장을 초래할 때라 하여 사업자의 자의적인 해석에 의해 계약을 해제할 수 있게 하는 바, 이는 사업자에게 법률에서 규정하고 있지 아니하는 해제권을 부여하거나, 법률의 규정에 의한 해제권의 사용요건을 완화하여 고객에 대하여 부당하게 불이익을 줄 우려가 있는 조항이다."
    ],
    "relateLaword": [
        "제9조(계약의 해제,해지) \n계약의 해제,해지에 관하여 정하고 있는 약관의 내용 중 다음 각 호의 어느 하나에 해당되는 내용을 정하고 있는 조항은 무효로 한다.\n2. 사업자에게 법률에서 규정하고 있지 아니하는 해제권 또는 해지권을 부여하여 고객에게 부당하게 불이익을 줄 우려가 있는 조항"
    ],
    "unfavorableProvision": "2"
}