{
    "clauseField": "1",
    "ftcCnclsns": "1",
    "clauseArticle": [
        "제26조(영업상의 준수사항)\n을 은  을 의 000  점을 경영하는데 있어서 계약기간 중 다음에 정한 사항을 준수하여야한다.\n제2호 을 의 000  점 이외의 장소에서  000 시스템 에 의한 사업 내지는 영업활동과 동일하거나 유사한 영업행위를 행하여서는 안 된다.",
        "을 의 000  점 이외의 장소에서  000 시스템 에 의한 사업 내지는 영업활동과 동일하거나 유사한 영업행위를 행하여서는 안 된다."
    ],
    "dvAntageous": "2",
    "illdcssBasiss": [
        "금지되는 업무 범위를 가맹사업법상의 동일한 영업행위 뿐만 아니라 유사한 영업행위 까지 확대하고 있어 가맹점사업자에게 불리하고, 유사한 영업행위란 표현도 매우 불명확하고 포괄적인 개념이므로 가맹점사업자에게 금지되는 영업행위가 어디까지인지 예측하기 곤란하게 만드는 측면이 있다. 고객에게 부당하게 불리한 조항이다."
    ],
    "relateLaword": [
        "제6조(일반원칙) \n② 약관의 내용 중 다음 각 호의 어느 하나에 해당하는 내용을 정하고 있는 조항은 공정성을 잃은 것으로 추정된다.\n  1. 고객에게 부당하게 불리한 조항"
    ],
    "unfavorableProvision": "1"
}