{
    "clauseField": "39",
    "ftcCnclsns": "1",
    "clauseArticle": [
        "제4장 사용료\n③ 과납금 산출 방식은 입회비에서 수강료(골프 18만원, 스쿼시,요가,째즈,나이트댄스 각각 12만원, 헬스 7만원) 용품대금, 환불약정금(회비의 10퍼센트) 및 부과세를 공제한 금액으로 한다. \n④ 사용기간을 월단위로 정산하며(1회 사용 한달 적용), 미사용한 상태에서 기간이 만료된 회원권은 사용권을 주장할 수 있다."
    ],
    "dvAntageous": "2",
    "illdcssBasiss": [
        "부가가치세(약관상 부과세)는 피청구인이 책정한 수강료에 이미 포함되어 있음에도 불구하고 수강료와는 별도로 부가가치세를 중복 공제하도록 정하고 있다. 또한 1회 이용의 경우에도 1월분 수강료 등 이용요금을 전액 공제하도록 정하고 있는 바,이는 이용일수에 해당하는 이용금액 및 총 이용금액의 10퍼센트를 공제하도록 한 소비자피해보상규정 및 일반의 거래관행에 비추어 부당하게 과중한 손해배상액의 예정이다."
    ],
    "relateLaword": [
        "제8조(손해배상액의 예정) \n고객에게 부당하게 과중한 지연 손해금 등의 손해배상 의무를 부담시키는 약관 조항은 무효로 한다."
    ],
    "unfavorableProvision": "2"
}